MANIFEST.in
setup.cfg
setup.py
array_tags/__init__.py
array_tags/fields.py
array_tags/lookups.py
array_tags/managers.py
array_tags/widgets.py
array_tags/static/admin/css/array-tag.css
array_tags/static/admin/js/array-tag.js
django_array_tags.egg-info/PKG-INFO
django_array_tags.egg-info/SOURCES.txt
django_array_tags.egg-info/dependency_links.txt
django_array_tags.egg-info/not-zip-safe
django_array_tags.egg-info/requires.txt
django_array_tags.egg-info/top_level.txt