Metadata-Version: 1.1
Name: django-array-tags
Version: 0.2.1
Summary: Simple Tagging for Django using PG ArrayField
Home-page: http://github.com/funkybob/django-array-tags
Author: Curtis Maloney
Author-email: curtis@tinbrain.net
License: UNKNOWN
Platform: UNKNOWN
Classifier: Environment :: Web Environment
Classifier: Framework :: Django
Classifier: License :: OSI Approved :: BSD License
Classifier: Operating System :: OS Independent
Classifier: Programming Language :: Python
Classifier: Programming Language :: Python :: 2.7
Classifier: Programming Language :: Python :: 3.3
Classifier: Programming Language :: Python :: 3.4
Classifier: Programming Language :: Python :: 3.5
Classifier: Programming Language :: Python :: Implementation :: PyPy
Requires: Django (>=1.7)
